allos/__init__.py
allos/__version__.py
allos/agent/__init__.py
allos/agent/agent.py
allos/agent/base.py
allos/agent/context.py
allos/agent/planner.py
allos/agent/session.py
allos/cli/__init__.py
allos/cli/commands.py
allos/cli/interactive.py
allos/cli/logo.py
allos/cli/main.py
allos/cli/output.py
allos/config/__init__.py
allos/config/defaults.py
allos/config/schema.py
allos/config/settings.py
allos/context/__init__.py
allos/context/cache.py
allos/context/compactor.py
allos/context/manager.py
allos/plugins/__init__.py
allos/plugins/base.py
allos/plugins/loader.py
allos/plugins/manager.py
allos/providers/__init__.py
allos/providers/anthropic.py
allos/providers/base.py
allos/providers/cohere.py
allos/providers/google.py
allos/providers/ollama.py
allos/providers/openai.py
allos/providers/registry.py
allos/providers/utils.py
allos/templates/__init__.py
allos/templates/code_reviewer.py
allos/templates/documentation_writer.py
allos/templates/security_auditor.py
allos/templates/sre_agent.py
allos/tools/__init__.py
allos/tools/base.py
allos/tools/permissions.py
allos/tools/registry.py
allos/tools/execution/__init__.py
allos/tools/execution/python.py
allos/tools/execution/shell.py
allos/tools/filesystem/__init__.py
allos/tools/filesystem/directory.py
allos/tools/filesystem/edit.py
allos/tools/filesystem/read.py
allos/tools/filesystem/write.py
allos/tools/mcp/__init__.py
allos/tools/mcp/client.py
allos/tools/mcp/server.py
allos/tools/web/__init__.py
allos/tools/web/fetch.py
allos/tools/web/search.py
allos/utils/__init__.py
allos/utils/errors.py
allos/utils/file_utils.py
allos/utils/logging.py
allos/utils/token_counter.py
allos_agent_sdk-0.0.1.dist-info/licenses/LICENSE
allos_agent_sdk-0.0.1.dist-info/METADATA
allos_agent_sdk-0.0.1.dist-info/WHEEL
allos_agent_sdk-0.0.1.dist-info/entry_points.txt
allos_agent_sdk-0.0.1.dist-info/top_level.txt
allos_agent_sdk-0.0.1.dist-info/RECORD
