Metadata-Version: 2.4
Name: allos-agent-sdk
Version: 0.0.1
Summary: The LLM-Agnostic Agentic Framework
Author-email: The Allos Community <Undiluted7027@proton.me>
License: MIT License
Project-URL: Homepage, https://github.com/Undiluted7027/allos-agent-sdk
Project-URL: Bug Tracker, https://github.com/Undiluted7027/allos-agent-sdk/issues
Project-URL: Documentation, https://github.com/Undiluted7027/allos-agent-sdk/tree/main/docs
Keywords: ai,agent,llm,sdk,openai,anthropic,agnostic,automation
Classifier: Development Status :: 5 - Production/Stable
Classifier: Operating System :: OS Independent
Classifier: Intended Audience :: Developers
Classifier: License :: OSI Approved :: MIT License
Classifier: Environment :: Console
Classifier: Programming Language :: Python :: 3
Classifier: Programming Language :: Python :: 3.9
Classifier: Programming Language :: Python :: 3.10
Classifier: Programming Language :: Python :: 3.11
Classifier: Programming Language :: Python :: 3.12
Classifier: Programming Language :: Python :: 3.13
Classifier: Topic :: Software Development :: Libraries :: Application Frameworks
Requires-Python: >=3.9
License-File: LICENSE
Requires-Dist: pydantic>=2.12.3
Requires-Dist: httpx>=0.28.1
Requires-Dist: rich>=14.2.0
Requires-Dist: click>=8.1.8
Requires-Dist: pyyaml>=6.0.3
Requires-Dist: tiktoken>=0.12.0
Provides-Extra: openai
Requires-Dist: openai>=2.6.1; extra == "openai"
Provides-Extra: anthropic
Requires-Dist: anthropic>=0.72.0; extra == "anthropic"
Provides-Extra: all
Requires-Dist: allos-agent-sdk[anthropic,openai]; extra == "all"
Provides-Extra: dev
Requires-Dist: pytest>=8.4.2; extra == "dev"
Requires-Dist: black>=25.9.0; extra == "dev"
Requires-Dist: ruff>=0.14.3; extra == "dev"
Requires-Dist: mypy>=1.18.2; extra == "dev"
Requires-Dist: pre-commit>=4.3.0; extra == "dev"
Requires-Dist: pytest-cov>=7.0.0; extra == "dev"
Requires-Dist: pytest-mock>=3.15.1; extra == "dev"
Requires-Dist: pytest-dotenv>=0.5.2; extra == "dev"
Requires-Dist: python-dotenv>=1.2.1; extra == "dev"
Dynamic: license-file
